Metadata-Version: 1.2
Name: wsPerf
Version: 0.1
Summary: wsPerf Namespace: Web Services Performers (wsPerf)  name base for a collection of libraries and command modules for webServices.
Home-page: http://www.by-star.net/PLPC/180047
Author: Mohsen Banan
Author-email: libre@mohsen.1.banan.byname.net
Maintainer: Mohsen Banan
Maintainer-email: libre@mohsen.1.banan.byname.net
License: AGPL
Download-URL: http://www.by-star.net/PLPC/180047
Platform: UNKNOWN
Classifier: Development Status :: 5 - Production/Stable
Classifier: Intended Audience :: Developers
Classifier: License :: OSI Approved :: GNU Affero General Public License v3
Classifier: Operating System :: POSIX
Classifier: Programming Language :: Python
Classifier: Topic :: Software Development :: Libraries
Classifier: Topic :: Software Development :: Libraries :: Python Modules
